msions/__init__.py
msions/encyclopedia.py
msions/hardklor.py
msions/kronik.py
msions/msplot.py
msions/mzml.py
msions/percolator.py
msions/utils.py
msions-0.4.0.dist-info/LICENSE
msions-0.4.0.dist-info/WHEEL
msions-0.4.0.dist-info/METADATA
msions-0.4.0.dist-info/RECORD
