Metadata-Version: 2.1
Name: msions
Version: 0.4.0
Summary: A python package for creating MS TIC and ion plots
License: Apache-2.0
Author: Danielle A. Faivre
Requires-Python: >=3.9
Classifier: License :: OSI Approved :: Apache Software License
Classifier: Programming Language :: Python :: 3
Classifier: Programming Language :: Python :: 3.9
Classifier: Programming Language :: Python :: 3.10
Classifier: Programming Language :: Python :: 3.11
Requires-Dist: matplotlib (>=3.5,<3.6)
Requires-Dist: pandas (>=1.5.2)
Requires-Dist: pymzml (>=2.5.2)
Requires-Dist: seaborn (>=0.12.1)
